pycsvw/__init__.py
pycsvw/csvw.py
pycsvw/csvw_exceptions.py
pycsvw/generator_utils.py
pycsvw/nt_serializer.py
pycsvw/rdf_utils.py
pycsvw/scripts/__init__.py
pycsvw/scripts/cli.py
pycsvw-1.0.2.dist-info/DESCRIPTION.rst
pycsvw-1.0.2.dist-info/METADATA
pycsvw-1.0.2.dist-info/RECORD
pycsvw-1.0.2.dist-info/WHEEL
pycsvw-1.0.2.dist-info/entry_points.txt
pycsvw-1.0.2.dist-info/metadata.json
pycsvw-1.0.2.dist-info/top_level.txt
