Metadata-Version: 2.0
Name: pycsvw
Version: 1.0.2
Summary: Generate JSON and RDF from csv files with metadata
Home-page: https://github.com/bloomberg/pycsvw
Author: Dev Ramudit, Erman Korkut
Author-email: dramudit2@bloomberg.net, ekorkut1@bloomberg.net
License: UNKNOWN
Keywords: csv metadata rdf json csvw
Platform: UNKNOWN
Classifier: Development Status :: 4 - Beta
Classifier: Intended Audience :: Developers
Classifier: Programming Language :: Python :: 2.7
Classifier: Programming Language :: Python :: 3.4
Classifier: Topic :: Software Development :: Libraries :: Python Modules
Requires-Dist: click
Requires-Dist: future
Requires-Dist: python-dateutil
Requires-Dist: rdflib
Requires-Dist: rdflib-jsonld
Requires-Dist: six
